mo_gym/__init__.py
mo_gym/evaluation.py
mo_gym/utils.py
mo_gym/breakable_bottles/__init__.py
mo_gym/breakable_bottles/breakable_bottles.py
mo_gym/continuous_mountain_car/__init__.py
mo_gym/continuous_mountain_car/continuous_mountain_car.py
mo_gym/deep_sea_treasure/__init__.py
mo_gym/deep_sea_treasure/deep_sea_treasure.py
mo_gym/deep_sea_treasure/assets/submarine.png
mo_gym/deep_sea_treasure/assets/treasure.png
mo_gym/fishwood/__init__.py
mo_gym/fishwood/fishwood.py
mo_gym/fishwood/assets/Kawa.jpg
mo_gym/fishwood/assets/Mori.jpg
mo_gym/four_room/__init__.py
mo_gym/four_room/four_room.py
mo_gym/fruit_tree/__init__.py
mo_gym/fruit_tree/fruit_tree.py
mo_gym/highway/__init__.py
mo_gym/highway/highway.py
mo_gym/mario/__init__.py
mo_gym/mario/mario.py
mo_gym/minecart/__init__.py
mo_gym/minecart/mine_config.json
mo_gym/minecart/mine_config_det.json
mo_gym/minecart/minecart.py
mo_gym/minecart/assets/cart.png
mo_gym/minecart/assets/mine.png
mo_gym/mountain_car/__init__.py
mo_gym/mountain_car/mountain_car.py
mo_gym/mujoco/__init__.py
mo_gym/mujoco/half_cheetah.py
mo_gym/mujoco/hopper.py
mo_gym/reacher/__init__.py
mo_gym/reacher/reacher.py
mo_gym/resource_gathering/__init__.py
mo_gym/resource_gathering/resource_gathering.py
mo_gym/resource_gathering/assets/gem.png
mo_gym/resource_gathering/assets/gold.png
mo_gym/resource_gathering/assets/home.png
mo_gym/resource_gathering/assets/stickerman.png
mo_gym/resource_gathering/assets/sword.png
mo_gym/water_reservoir/__init__.py
mo_gym/water_reservoir/dam_env.py
mo_gym-0.2.1.dist-info/LICENSE
mo_gym-0.2.1.dist-info/METADATA
mo_gym-0.2.1.dist-info/WHEEL
mo_gym-0.2.1.dist-info/top_level.txt
mo_gym-0.2.1.dist-info/RECORD
